aiogateway/__init__.py
aiogateway/api.py
aiogateway/asgi.py
aiogateway/client.py
aiogateway/docs.py
aiogateway/helpers.py
aiogateway-0.0.1.dist-info/METADATA
aiogateway-0.0.1.dist-info/WHEEL
aiogateway-0.0.1.dist-info/RECORD
